PyKIPass/PyKIPass.py
PyKIPass/URLs.py
PyKIPass/__init__.py
PyKIPass/exceptions.py
PyKIPass-1.2.0.dist-info/LICENSE
PyKIPass-1.2.0.dist-info/METADATA
PyKIPass-1.2.0.dist-info/WHEEL
PyKIPass-1.2.0.dist-info/top_level.txt
PyKIPass-1.2.0.dist-info/RECORD
