Metadata-Version: 2.1
Name: PyKIPass
Version: 1.2.0
Summary: Python wrapper for KIPass
Home-page: https://github.com/alus20x/PyKIPass
Author: alus20x
Author-email: alus20x@gmail.com
License: MIT
Platform: UNKNOWN
License-File: LICENSE
